assets.py
bash_script_maker.py
custom_dialogs.py
localization.py
syntax_highlighter.py
bash_script_maker-1.11.0.dist-info/LICENSE
bash_script_maker-1.11.0.dist-info/METADATA
bash_script_maker-1.11.0.dist-info/WHEEL
bash_script_maker-1.11.0.dist-info/entry_points.txt
bash_script_maker-1.11.0.dist-info/top_level.txt
bash_script_maker-1.11.0.dist-info/RECORD
