Metadata-Version: 2.1
Name: bash-script-maker
Version: 1.11.0
Summary: Ein GUI-Programm zur Erstellung von Bash-Scripts mit visueller Unterstützung
Home-page: https://github.com/securebitsorg/bash-script-maker
Author: Marcel Dellmann
Author-email: Marcel Dellmann <support@secure-bits.org>
Maintainer-email: Marcel Dellmann <support@secure-bits.org>
License: MIT
Project-URL: Homepage, https://github.com/securebitsorg/bash-script-maker
Project-URL: Documentation, https://github.com/securebitsorg/bash-script-maker#readme
Project-URL: Repository, https://github.com/securebitsorg/bash-script-maker
Project-URL: Bug Reports, https://github.com/securebitsorg/bash-script-maker/issues
Project-URL: Changelog, https://github.com/securebitsorg/bash-script-maker/blob/main/CHANGELOG.md
Keywords: bash,script,gui,editor,generator,linux
Classifier: Development Status :: 4 - Beta
Classifier: Intended Audience :: Developers
Classifier: Intended Audience :: End Users/Desktop
Classifier: Operating System :: POSIX :: Linux
Classifier: Programming Language :: Python :: 3
Classifier: Programming Language :: Python :: 3.8
Classifier: Programming Language :: Python :: 3.9
Classifier: Programming Language :: Python :: 3.10
Classifier: Programming Language :: Python :: 3.11
Classifier: Programming Language :: Python :: 3.12
Classifier: Topic :: Utilities
Classifier: Topic :: Text Editors :: Integrated Development Environments (IDE)
Classifier: Topic :: Software Development :: Code Generators
Requires-Python: >=3.8
License-File: LICENSE
Requires-Dist: ttkbootstrap>=1.10.1
Requires-Dist: pygments>=2.15.1
Requires-Dist: Pillow>=9.0.0
Provides-Extra: dev
Requires-Dist: pytest>=6.0.0; extra == "dev"
Requires-Dist: pytest-cov>=2.10.0; extra == "dev"
Requires-Dist: flake8>=3.8.0; extra == "dev"
Requires-Dist: black>=21.0.0; extra == "dev"
Requires-Dist: mypy>=0.800; extra == "dev"
Requires-Dist: tox>=3.20.0; extra == "dev"
Requires-Dist: twine>=3.0.0; extra == "dev"
Requires-Dist: build>=0.7.0; extra == "dev"
Requires-Dist: bandit>=1.7.0; extra == "dev"
